conf_root/ConfRoot.py
conf_root/Configuration.py
conf_root/__init__.py
conf_root/utils.py
conf_root/agents/BasicAgent.py
conf_root/agents/JsonAgent.py
conf_root/agents/YamlAgent.py
conf_root/agents/utils.py
conf_root_pure-0.5.0.dist-info/LICENSE
conf_root_pure-0.5.0.dist-info/METADATA
conf_root_pure-0.5.0.dist-info/WHEEL
conf_root_pure-0.5.0.dist-info/top_level.txt
conf_root_pure-0.5.0.dist-info/RECORD
